proxy_rotator/ProxyRotator.py
proxy_rotator/ProxyStorage.py
proxy_rotator/__init__.py
proxy_rotator/proxy_rotator.py
proxy_rotator/proxy_storage.py
proxy_rotator/proxy_types.py
proxy_rotator/schemas.py
dwarf_rotator-0.1.1.dist-info/METADATA
dwarf_rotator-0.1.1.dist-info/WHEEL
dwarf_rotator-0.1.1.dist-info/top_level.txt
dwarf_rotator-0.1.1.dist-info/RECORD
